dom_toml/__init__.py
dom_toml/decoder.py
dom_toml/encoder.py
dom_toml/parser.py
dom_toml/py.typed
dom_toml-2.1.0.dist-info/licenses/LICENSE
dom_toml-2.1.0.dist-info/WHEEL
dom_toml-2.1.0.dist-info/METADATA
dom_toml-2.1.0.dist-info/RECORD
